[
    {
        "hour": "2024-12-11 04:00:00",
        "total_volume": 2514.0
    },
    {
        "hour": "2024-12-11 03:00:00",
        "total_volume": 3223.0
    },
    {
        "hour": "2024-12-11 02:00:00",
        "total_volume": 5873.0
    },
    {
        "hour": "2024-12-11 01:00:00",
        "total_volume": 5086.0
    },
    {
        "hour": "2024-12-11 00:00:00",
        "total_volume": 5430.0
    },
    {
        "hour": "2024-12-10 23:00:00",
        "total_volume": 3945.0
    },
    {
        "hour": "2024-12-10 22:00:00",
        "total_volume": 3905.0
    },
    {
        "hour": "2024-12-10 21:00:00",
        "total_volume": 10283.0
    },
    {
        "hour": "2024-12-10 20:00:00",
        "total_volume": 10139.0
    }
]